mkds_py/__init__.py
mkds_py/kcl.py
mkds_py/nkm.py
mkds_py/utils.py
mkds_py-0.0.1.dist-info/METADATA
mkds_py-0.0.1.dist-info/WHEEL
mkds_py-0.0.1.dist-info/licenses/LICENSE.txt
mkds_py-0.0.1.dist-info/RECORD
