Metadata-Version: 2.4
Name: mkds_py
Version: 0.0.1
Summary: A lightweight library for parsing mariokart ds game files
Project-URL: Homepage, https://github.com/gg-blake/mkds-py
Project-URL: Issues, https://github.com/gg-blake/mkds-py/issues
Author-email: Blake Moody <blake@moody.mx>
License-Expression: Apache-2.0
License-File: LICENSE.txt
Classifier: Programming Language :: Python :: 3
Requires-Python: >=3.9
